{
    "$schema": "http://json-schema.org/draft-07/schema#",
    "additionalProperties": false,
    "definitions": {
        "AmplifyAppSyncSimulatorAuthenticationType": {
            "enum": [
                "AMAZON_COGNITO_USER_POOLS",
                "API_KEY",
                "AWS_IAM",
                "OPENID_CONNECT"
            ],
            "type": "string"
        }
    },
    "properties": {
        "appSyncConfig": {
            "additionalProperties": false,
            "properties": {
                "additionalAuthenticationProviders": {
                    "items": {
                        "anyOf": [
                            {
                                "additionalProperties": false,
                                "properties": {
                                    "authenticationType": {
                                        "enum": [
                                            "API_KEY"
                                        ],
                                        "type": "string"
                                    }
                                },
                                "type": "object"
                            },
                            {
                                "additionalProperties": false,
                                "properties": {
                                    "authenticationType": {
                                        "enum": [
                                            "AWS_IAM"
                                        ],
                                        "type": "string"
                                    }
                                },
                                "type": "object"
                            },
                            {
                                "additionalProperties": false,
                                "properties": {
                                    "authenticationType": {
                                        "enum": [
                                            "AMAZON_COGNITO_USER_POOLS"
                                        ],
                                        "type": "string"
                                    },
                                    "cognitoUserPoolConfig": {
                                        "additionalProperties": false,
                                        "properties": {
                                            "AppIdClientRegex": {
                                                "type": "string"
                                            }
                                        },
                                        "type": "object"
                                    }
                                },
                                "type": "object"
                            },
                            {
                                "additionalProperties": false,
                                "properties": {
                                    "authenticationType": {
                                        "enum": [
                                            "OPENID_CONNECT"
                                        ],
                                        "type": "string"
                                    },
                                    "openIDConnectConfig": {
                                        "additionalProperties": false,
                                        "properties": {
                                            "ClientId": {
                                                "type": "string"
                                            },
                                            "Issuer": {
                                                "type": "string"
                                            }
                                        },
                                        "type": "object"
                                    }
                                },
                                "type": "object"
                            }
                        ]
                    },
                    "type": "array"
                },
                "apiKey": {
                    "type": "string"
                },
                "defaultAuthenticationType": {
                    "anyOf": [
                        {
                            "additionalProperties": false,
                            "properties": {
                                "authenticationType": {
                                    "enum": [
                                        "API_KEY"
                                    ],
                                    "type": "string"
                                }
                            },
                            "type": "object"
                        },
                        {
                            "additionalProperties": false,
                            "properties": {
                                "authenticationType": {
                                    "enum": [
                                        "AWS_IAM"
                                    ],
                                    "type": "string"
                                }
                            },
                            "type": "object"
                        },
                        {
                            "additionalProperties": false,
                            "properties": {
                                "authenticationType": {
                                    "enum": [
                                        "AMAZON_COGNITO_USER_POOLS"
                                    ],
                                    "type": "string"
                                },
                                "cognitoUserPoolConfig": {
                                    "additionalProperties": false,
                                    "properties": {
                                        "AppIdClientRegex": {
                                            "type": "string"
                                        }
                                    },
                                    "type": "object"
                                }
                            },
                            "type": "object"
                        },
                        {
                            "additionalProperties": false,
                            "properties": {
                                "authenticationType": {
                                    "enum": [
                                        "OPENID_CONNECT"
                                    ],
                                    "type": "string"
                                },
                                "openIDConnectConfig": {
                                    "additionalProperties": false,
                                    "properties": {
                                        "ClientId": {
                                            "type": "string"
                                        },
                                        "Issuer": {
                                            "type": "string"
                                        }
                                    },
                                    "type": "object"
                                }
                            },
                            "type": "object"
                        }
                    ]
                },
                "name": {
                    "type": "string"
                }
            },
            "type": "object"
        },
        "executionContext": {
            "additionalProperties": false,
            "properties": {
                "headers": {
                    "additionalProperties": {
                        "type": "string"
                    },
                    "type": "object"
                },
                "jwt": {
                    "additionalProperties": false,
                    "properties": {
                        "aud": {
                            "type": "string"
                        },
                        "cognito:username": {
                            "type": "string"
                        },
                        "exp": {
                            "type": "number"
                        },
                        "iat": {
                            "type": "number"
                        },
                        "iss": {
                            "type": "string"
                        },
                        "nbf": {
                            "type": "number"
                        },
                        "sub": {
                            "type": "string"
                        },
                        "username": {
                            "type": "string"
                        }
                    },
                    "type": "object"
                },
                "requestAuthorizationMode": {
                    "$ref": "#/definitions/AmplifyAppSyncSimulatorAuthenticationType"
                },
                "sourceIp": {
                    "type": "string"
                }
            },
            "type": "object"
        },
        "graphQLRequest": {
            "additionalProperties": false,
            "properties": {
                "operationName": {
                    "type": "string"
                },
                "query": {
                    "type": "string"
                },
                "variables": {
                    "additionalProperties": {
                    },
                    "type": "object"
                }
            },
            "type": "object"
        },
        "renderContext": {
            "additionalProperties": false,
            "properties": {
                "arguments": {
                    "additionalProperties": true,
                    "properties": {
                    },
                    "type": "object"
                },
                "error": {
                },
                "prevResult": {
                },
                "result": {
                },
                "source": {
                    "additionalProperties": true,
                    "properties": {
                    },
                    "type": "object"
                },
                "stash": {
                    "additionalProperties": true,
                    "properties": {
                    },
                    "type": "object"
                }
            },
            "type": "object"
        },
        "schema": {
            "type": "string"
        },
        "template": {
            "type": "string"
        },
        "templateName": {
            "type": "string"
        }
    },
    "type": "object"
}

